jwt/__init__.py
jwt/algorithms.py
jwt/api_jwk.py
jwt/api_jws.py
jwt/api_jwt.py
jwt/exceptions.py
jwt/help.py
jwt/jwk_set_cache.py
jwt/jwks_client.py
jwt/py.typed
jwt/types.py
jwt/utils.py
jwt/warnings.py
PyJWT-2.10.0.dist-info/AUTHORS.rst
PyJWT-2.10.0.dist-info/LICENSE
PyJWT-2.10.0.dist-info/METADATA
PyJWT-2.10.0.dist-info/WHEEL
PyJWT-2.10.0.dist-info/top_level.txt
PyJWT-2.10.0.dist-info/RECORD
